README.md
setup.py
PySigmoid/BitUtils.py
PySigmoid/Posit.py
PySigmoid/Quire.py
PySigmoid/__init__.py
PySigmoid.egg-info/PKG-INFO
PySigmoid.egg-info/SOURCES.txt
PySigmoid.egg-info/dependency_links.txt
PySigmoid.egg-info/not-zip-safe
PySigmoid.egg-info/requires.txt
PySigmoid.egg-info/top_level.txt