Metadata-Version: 1.2
Name: PySigmoid
Version: 0.2
Summary: A Python Library that Implements Posit
Home-page: https://github.com/mightymercado/PySigmoid
Author: Ken Mercado
Author-email: mightymercado@gmail.com
License: MIT
Platform: UNKNOWN
Requires-Python: >=3
